[
  {
    "라운드": 1,
    "외계 동물 수": 0,
    "사각형-가로": 9,
    "사각형-세로": 9,
    "사각형-지뢰 개수": 10,
    "육각형-길이": 6,
    "육각형-지뢰 개수": 12
  },
  {
    "라운드": 2,
    "외계 동물 수": 0,
    "사각형-가로": 12,
    "사각형-세로": 12,
    "사각형-지뢰 개수": 20,
    "육각형-길이": 7,
    "육각형-지뢰 개수": 19
  },
  {
    "라운드": 3,
    "외계 동물 수": 1,
    "사각형-가로": 14,
    "사각형-세로": 14,
    "사각형-지뢰 개수": 30,
    "육각형-길이": 8,
    "육각형-지뢰 개수": 27
  },
  {
    "라운드": 4,
    "외계 동물 수": 1,
    "사각형-가로": 16,
    "사각형-세로": 16,
    "사각형-지뢰 개수": 40,
    "육각형-길이": 9,
    "육각형-지뢰 개수": 36
  },
  {
    "라운드": 5,
    "외계 동물 수": 1,
    "사각형-가로": 16,
    "사각형-세로": 20,
    "사각형-지뢰 개수": 55,
    "육각형-길이": 10,
    "육각형-지뢰 개수": 48
  },
  {
    "라운드": 6,
    "외계 동물 수": 2,
    "사각형-가로": 16,
    "사각형-세로": 24,
    "사각형-지뢰 개수": 70,
    "육각형-길이": 11,
    "육각형-지뢰 개수": 62
  },
  {
    "라운드": 7,
    "외계 동물 수": 2,
    "사각형-가로": 16,
    "사각형-세로": 28,
    "사각형-지뢰 개수": 85,
    "육각형-길이": 12,
    "육각형-지뢰 개수": 97
  },
  {
    "라운드": 8,
    "외계 동물 수": 2,
    "사각형-가로": 16,
    "사각형-세로": 30,
    "사각형-지뢰 개수": 99,
    "육각형-길이": 13,
    "육각형-지뢰 개수": 98
  },
  {
    "라운드": 9,
    "외계 동물 수": 3,
    "사각형-가로": 17,
    "사각형-세로": 30,
    "사각형-지뢰 개수": 110,
    "육각형-길이": 13,
    "육각형-지뢰 개수": 103
  },
  {
    "라운드": 10,
    "외계 동물 수": 3,
    "사각형-가로": 18,
    "사각형-세로": 30,
    "사각형-지뢰 개수": 120,
    "육각형-길이": 14,
    "육각형-지뢰 개수": 125
  }
]